beam/__init__.py
beam/config.py
beam/context.py
beam/settings.py
beam/site.py
beam/builders/__init__.py
beam/builders/base.py
beam/builders/blog.py
beam/builders/pages.py
beam/builders/sitemap.py
beam/builders/static_files.py
beam/cli/__init__.py
beam/cli/config.py
beam/cli/i18n.py
beam/cli/main.py
beam/cli/up.py
beam/i18n/__init__.py
beam/i18n/config.py
beam/i18n/markdown.py
beam/i18n/strings.py
beam/i18n/helpers/__init__.py
beam/i18n/helpers/hash.py
beam/i18n/helpers/languages.py
beam/i18n/helpers/serialize.py
beam/i18n/helpers/translate.py
beam/i18n/helpers/yaml.py
beam/loaders/__init__.py
beam/loaders/base.py
beam/loaders/file.py
beam/processors/__init__.py
beam/processors/base.py
beam/processors/jinja.py
beam/processors/markdown.py
beam/processors/plain.py
beam_up-1.0.41.dist-info/METADATA
beam_up-1.0.41.dist-info/WHEEL
beam_up-1.0.41.dist-info/entry_points.txt
beam_up-1.0.41.dist-info/top_level.txt
beam_up-1.0.41.dist-info/RECORD
