Metadata-Version: 2.1
Name: beam-up
Version: 1.0.41
Summary: A simple yet powerful static site generator aimed at product pages (not blogs).
Home-page: https://github.com/adewes/beam
Author: Andreas Dewes - 7scientists
Author-email: andreas.dewes@7scientists.com
License: MIT
Platform: UNKNOWN
Requires-Python: >=3
Requires-Dist: requests
Requires-Dist: click
Requires-Dist: pyyaml
Requires-Dist: markdown2
Requires-Dist: jinja2
Requires-Dist: pygments
Requires-Dist: Pillow
